bbuddy/bbuddy.py
bbuddy/bindump.py
bbuddy/dbdump.py
bbuddy/fffind.py
bbuddy/git_consolidate.py
bbuddy/ppgrep.py
bbuddy-0.0.2.dist-info/METADATA
bbuddy-0.0.2.dist-info/WHEEL
bbuddy-0.0.2.dist-info/entry_points.txt
bbuddy-0.0.2.dist-info/licenses/LICENSE.txt
bbuddy-0.0.2.dist-info/RECORD
