Metadata-Version: 2.4
Name: bbuddy
Version: 0.0.2
Summary: collection of helpful bash tools
Project-URL: Homepage, https://github.com/dickjustice/bbuddy
Author-email: Dick Justice <dickjustice@x2400.com>
License-File: LICENSE.txt
Classifier: License :: OSI Approved :: MIT License
Classifier: Operating System :: OS Independent
Classifier: Programming Language :: Python :: 3
Requires-Python: >=3.8
